{
  "name": "Smart Ticket Triage Starter Workflow",
  "nodes": [
    {
      "parameters": {},
      "id": "e44d59f5-1c5c-4b5b-86d1-cf1b37b6dc19",
      "name": "When clicking 'Execute workflow'",
      "type": "n8n-nodes-base.manualTrigger",
      "typeVersion": 1,
      "position": [
        100,
        240
      ]
    },
    {
      "parameters": {
        "operation": "read",
        "sheetId": "YOUR_SPREADSHEET_ID_HERE",
        "range": "input!A:K",
        "options": {}
      },
      "id": "c1f7b036-7c05-4c07-b3ea-37d45e4ab914",
      "name": "Get row(s) in sheet",
      "type": "n8n-nodes-base.googleSheets",
      "typeVersion": 4,
      "position": [
        320,
        240
      ],
      "credentials": {
        "googleSheetsOAuth2Api": {
          "id": "mock-credentials-id",
          "name": "Google Sheets Connection"
        }
      }
    }
  ],
  "connections": {
    "When clicking 'Execute workflow'": {
      "main": [
        [
          {
            "node": "Get row(s) in sheet",
            "type": "main",
            "index": 0
          }
        ]
      ]
    }
  },
  "active": false,
  "settings": {
    "executionTimeout": 300
  },
  "versionId": "starter-bare-minimum-v1.0",
  "meta": {
    "templateCredsSetupCompleted": true
  }
}
